pathstr/__init__.py
tests/__init__.py
pathstr-0.2.0.dist-info/LICENSE
pathstr-0.2.0.dist-info/METADATA
pathstr-0.2.0.dist-info/WHEEL
pathstr-0.2.0.dist-info/top_level.txt
pathstr-0.2.0.dist-info/RECORD
