Metadata-Version: 2.1
Name: pathstr
Version: 0.2.0
Summary: Path string library helps developers to work with strings path. It works similar to standard pathlib.
Home-page: https://github.com/alfred82santa/pathstr
Author: Alfred Santacatalina
Author-email: alfred82santa@gmail.com
License: LGPLv3
Keywords: string path
Platform: UNKNOWN
Classifier: Development Status :: 4 - Beta
Classifier: Intended Audience :: Developers
Classifier: License :: OSI Approved :: GNU Lesser General Public License v3 (LGPLv3)
Classifier: Programming Language :: Python :: 3.6
Classifier: Programming Language :: Python :: 3.7
